CHANGELOG.rst
COPYING.txt
MANIFEST.in
README.rst
requirements.txt
setup.cfg
setup.py
resources/__init__.py
resources/docs/coffee_machine.svg
resources/sdist/__init__.py
resources/sdist/test_command.py
resources/sdist/utils.py
src/pylstar/ActiveKnowledgeBase.py
src/pylstar/FakeActiveKnowledgeBase.py
src/pylstar/KnowledgeBase.py
src/pylstar/KnowledgeBaseStats.py
src/pylstar/KnowledgeTree.py
src/pylstar/LSTAR.py
src/pylstar/Letter.py
src/pylstar/ObservationTable.py
src/pylstar/OutputQuery.py
src/pylstar/Word.py
src/pylstar/__init__.py
src/pylstar/release.py
src/pylstar.egg-info/PKG-INFO
src/pylstar.egg-info/SOURCES.txt
src/pylstar.egg-info/dependency_links.txt
src/pylstar.egg-info/requires.txt
src/pylstar.egg-info/top_level.txt
src/pylstar/automata/Automata.py
src/pylstar/automata/DOTParser.py
src/pylstar/automata/State.py
src/pylstar/automata/Transition.py
src/pylstar/automata/__init__.py
src/pylstar/eqtests/RandomWalkMethod.py
src/pylstar/eqtests/WpMethodEQ.py
src/pylstar/eqtests/__init__.py
src/pylstar/tools/Decorators.py
src/pylstar/tools/__init__.py