Metadata-Version: 1.1
Name: pylstar
Version: 0.1.2
Summary: Implementation of the LSTAR Grammatical Inference Algorithm
Home-page: https://github.com/gbossert/pylstar
Author: Georges Bossert
Author-email: gbossert@miskin.fr
License: GPLv3
Download-URL: https://github.com/gbossert/pylstar
Keywords: LSTAR,Angluin,Grammar,Inference
Platform: Linux_x86
Platform: Linux_x64
